LuFeixuechengPythonRumenDaoJingtongFix1/README.md
LuFeixuechengPythonRumenDaoJingtongFix1/__init__.py
LuFeixuechengPythonRumenDaoJingtongFix1/__main__.py
LuFeixuechengPythonRumenDaoJingtongFix1/file.epub
LuFeixuechengPythonRumenDaoJingtongFix1/index.html
LuFeixuechengPythonRumenDaoJingtongFix1/css/__init__.py
LuFeixuechengPythonRumenDaoJingtongFix1/css/annotations.css
LuFeixuechengPythonRumenDaoJingtongFix1/css/main.css
LuFeixuechengPythonRumenDaoJingtongFix1/css/normalize.css
LuFeixuechengPythonRumenDaoJingtongFix1/css/popup.css
LuFeixuechengPythonRumenDaoJingtongFix1/font/__init__.py
LuFeixuechengPythonRumenDaoJingtongFix1/font/fontello.eot
LuFeixuechengPythonRumenDaoJingtongFix1/font/fontello.svg
LuFeixuechengPythonRumenDaoJingtongFix1/font/fontello.ttf
LuFeixuechengPythonRumenDaoJingtongFix1/font/fontello.woff
LuFeixuechengPythonRumenDaoJingtongFix1/img/__init__.py
LuFeixuechengPythonRumenDaoJingtongFix1/img/annotator-glyph-sprite.png
LuFeixuechengPythonRumenDaoJingtongFix1/img/annotator-icon-sprite.png
LuFeixuechengPythonRumenDaoJingtongFix1/img/apple-touch-icon.png
LuFeixuechengPythonRumenDaoJingtongFix1/img/cancelfullscreen.png
LuFeixuechengPythonRumenDaoJingtongFix1/img/close.png
LuFeixuechengPythonRumenDaoJingtongFix1/img/fullscreen.png
LuFeixuechengPythonRumenDaoJingtongFix1/img/loader.gif
LuFeixuechengPythonRumenDaoJingtongFix1/img/menu-icon.png
LuFeixuechengPythonRumenDaoJingtongFix1/img/save.png
LuFeixuechengPythonRumenDaoJingtongFix1/img/saved.png
LuFeixuechengPythonRumenDaoJingtongFix1/img/settings-s.png
LuFeixuechengPythonRumenDaoJingtongFix1/img/settings.png
LuFeixuechengPythonRumenDaoJingtongFix1/img/star.png
LuFeixuechengPythonRumenDaoJingtongFix1/js/__init__.py
LuFeixuechengPythonRumenDaoJingtongFix1/js/epub.js
LuFeixuechengPythonRumenDaoJingtongFix1/js/epub.min.js
LuFeixuechengPythonRumenDaoJingtongFix1/js/epub.min.map
LuFeixuechengPythonRumenDaoJingtongFix1/js/hooks.min.js
LuFeixuechengPythonRumenDaoJingtongFix1/js/hooks.min.map
lu_feixuecheng_python_rumen_dao_jingtong_fix1-2025.3.25.1.dist-info/METADATA
lu_feixuecheng_python_rumen_dao_jingtong_fix1-2025.3.25.1.dist-info/WHEEL
lu_feixuecheng_python_rumen_dao_jingtong_fix1-2025.3.25.1.dist-info/entry_points.txt
lu_feixuecheng_python_rumen_dao_jingtong_fix1-2025.3.25.1.dist-info/top_level.txt
lu_feixuecheng_python_rumen_dao_jingtong_fix1-2025.3.25.1.dist-info/RECORD
